robotic/DataGen.pyi
robotic/__init__.py
robotic/_robotic.pyi
robotic/_robotic.so
robotic/algo.pyi
robotic/librai.so
robotic/manipulation.py
robotic/meshTool
robotic/mujoco-import.py
robotic/render.py
robotic/ry-bot
robotic/ry-h5info
robotic/ry-info
robotic/ry-meshTool
robotic/ry-test
robotic/ry-urdfConvert.py
robotic/ry-view
robotic/test.pyi
robotic/version.py
robotic/include/rai/Algo/MLcourse.h
robotic/include/rai/Algo/RidgeRegression.h
robotic/include/rai/Algo/SplineCtrlFeed.h
robotic/include/rai/Algo/ann.h
robotic/include/rai/Algo/dataNeighbored.h
robotic/include/rai/Algo/eigenValues.h
robotic/include/rai/Algo/gaussianProcess.h
robotic/include/rai/Algo/gpOp.h
robotic/include/rai/Algo/hungarian.h
robotic/include/rai/Algo/kalman.h
robotic/include/rai/Algo/marching_cubes.h
robotic/include/rai/Algo/minimalSpanningTree.h
robotic/include/rai/Algo/priorityQueue.h
robotic/include/rai/Algo/rungeKutta.h
robotic/include/rai/Algo/spline.h
robotic/include/rai/Algo/trilinear.h
robotic/include/rai/Algo/Lewiner/LookUpTable.h
robotic/include/rai/Algo/Lewiner/MarchingCubes.h
robotic/include/rai/Control/CtrlMsgs.h
robotic/include/rai/Control/CtrlObjective.h
robotic/include/rai/Control/CtrlSet.h
robotic/include/rai/Control/CtrlSolver.h
robotic/include/rai/Control/CtrlSolvers.h
robotic/include/rai/Control/CtrlTargets.h
robotic/include/rai/Control/RTControllerSimulation.h
robotic/include/rai/Control/SecMPC.h
robotic/include/rai/Control/ShortPathMPC.h
robotic/include/rai/Control/TimingMPC.h
robotic/include/rai/Control/WaypointMPC.h
robotic/include/rai/Control/control.h
robotic/include/rai/Control/ctrlMsg.h
robotic/include/rai/Control/timingOpt.h
robotic/include/rai/Core/array.h
robotic/include/rai/Core/array.ipp
robotic/include/rai/Core/arrayDouble.h
robotic/include/rai/Core/defines.h
robotic/include/rai/Core/graph.h
robotic/include/rai/Core/h5.h
robotic/include/rai/Core/plot.h
robotic/include/rai/Core/thread.h
robotic/include/rai/Core/util.h
robotic/include/rai/Core/util.ipp
robotic-0.3.5.dist-info/licenses/LICENSE
robotic-0.3.5.dist-info/METADATA
robotic-0.3.5.dist-info/WHEEL
robotic-0.3.5.dist-info/top_level.txt
robotic-0.3.5.dist-info/RECORD
