Metadata-Version: 2.4
Name: robotic
Version: 0.3.5
Summary: Robotic Control Interface & Manipulation Planning Library
Home-page: https://github.com/MarcToussaint/robotic/
Author: Marc Toussaint
Author-email: toussaint@tu-berlin.de
License-File: LICENSE
Dynamic: author
Dynamic: author-email
Dynamic: description
Dynamic: description-content-type
Dynamic: home-page
Dynamic: license-file
Dynamic: summary
